thonny_pyboard-0.2b1.dist-info/METADATA
thonny_pyboard-0.2b1.dist-info/RECORD
thonny_pyboard-0.2b1.dist-info/WHEEL
thonny_pyboard-0.2b1.dist-info/top_level.txt
thonnycontrib/pyboard/__init__.py
thonnycontrib/pyboard/api_stubs/_onewire.py
thonnycontrib/pyboard/api_stubs/array.py
thonnycontrib/pyboard/api_stubs/binascii.py
thonnycontrib/pyboard/api_stubs/builtins.py
thonnycontrib/pyboard/api_stubs/cmath.py
thonnycontrib/pyboard/api_stubs/collections.py
thonnycontrib/pyboard/api_stubs/dht.py
thonnycontrib/pyboard/api_stubs/errno.py
thonnycontrib/pyboard/api_stubs/framebuf.py
thonnycontrib/pyboard/api_stubs/gc.py
thonnycontrib/pyboard/api_stubs/hashlib.py
thonnycontrib/pyboard/api_stubs/heapq.py
thonnycontrib/pyboard/api_stubs/io.py
thonnycontrib/pyboard/api_stubs/json.py
thonnycontrib/pyboard/api_stubs/lcd160cr.py
thonnycontrib/pyboard/api_stubs/lcd160cr_test.py
thonnycontrib/pyboard/api_stubs/machine.py
thonnycontrib/pyboard/api_stubs/math.py
thonnycontrib/pyboard/api_stubs/micropython.py
thonnycontrib/pyboard/api_stubs/network.py
thonnycontrib/pyboard/api_stubs/onewire.py
thonnycontrib/pyboard/api_stubs/os.py
thonnycontrib/pyboard/api_stubs/pyb.py
thonnycontrib/pyboard/api_stubs/random.py
thonnycontrib/pyboard/api_stubs/re.py
thonnycontrib/pyboard/api_stubs/select.py
thonnycontrib/pyboard/api_stubs/socket.py
thonnycontrib/pyboard/api_stubs/stm.py
thonnycontrib/pyboard/api_stubs/struct.py
thonnycontrib/pyboard/api_stubs/sys.py
thonnycontrib/pyboard/api_stubs/time.py
thonnycontrib/pyboard/api_stubs/ubinascii.py
thonnycontrib/pyboard/api_stubs/ucollections.py
thonnycontrib/pyboard/api_stubs/uctypes.py
thonnycontrib/pyboard/api_stubs/uerrno.py
thonnycontrib/pyboard/api_stubs/uhashlib.py
thonnycontrib/pyboard/api_stubs/uheapq.py
thonnycontrib/pyboard/api_stubs/uio.py
thonnycontrib/pyboard/api_stubs/ujson.py
thonnycontrib/pyboard/api_stubs/umachine.py
thonnycontrib/pyboard/api_stubs/uos.py
thonnycontrib/pyboard/api_stubs/urandom.py
thonnycontrib/pyboard/api_stubs/ure.py
thonnycontrib/pyboard/api_stubs/uselect.py
thonnycontrib/pyboard/api_stubs/usocket.py
